pyhdwallet/__init__.py
pyhdwallet/ecpair.py
pyhdwallet/ecutils.py
pyhdwallet/hashutils.py
pyhdwallet/hdnode.py
pyhdwallet/networks.py
tests/__init__.py
tests/test_ecpair.py
tests/test_ecutils.py
tests/test_hdnode.py
pyhdwallet-1.0.0.dist-info/LICENSE
pyhdwallet-1.0.0.dist-info/METADATA
pyhdwallet-1.0.0.dist-info/WHEEL
pyhdwallet-1.0.0.dist-info/top_level.txt
pyhdwallet-1.0.0.dist-info/RECORD
