Metadata-Version: 2.1
Name: pyhdwallet
Version: 1.0.0
Summary: A Python lib for working with BIP32 (Hierarchical Deterministic Wallets)
Home-page: https://github.com/henriquetft/pyhdwallet
Author: henriquetft
Author-email: henrique@teofilo.me
License: BSD
Keywords: cryptocurrency,bitcoin,bip32,python,crypto,wallet,hierarchical-deterministic-wallets,hdwallet,bitcoincash
Platform: UNKNOWN
Classifier: Programming Language :: Python :: 3
Classifier: License :: OSI Approved :: BSD License
Classifier: Operating System :: OS Independent
Classifier: Intended Audience :: Developers
Requires-Python: >=3.6
Requires-Dist: base58 (==2.0.1)
Requires-Dist: ecdsa (==0.15)
Requires-Dist: six (==1.15.0)
